{
  "trade_id": "TRADE_20250123_141945_73",
  "token_address": "nXmXwBS9j55J5d8idenoDAnFgrUj3MueWnDeb7Rpump",
  "token_symbol": "DTJ",
  "entry_time": "2025-01-23T17:25:25.381032",
  "entry_price": 8.28679652802541e-06,
  "market_price": 7.205910024369923e-06,
  "position_size": 100,
  "confidence_score": 1.0,
  "features": {
    "momentum_5m": 0.0,
    "momentum_7m": 0.0,
    "trend_acceleration": 0.0,
    "price_volatility": 0.0,
    "price_change_15m": 0.0,
    "volume_momentum": 0.0
  },
  "token_age_minutes": 181.04338875
}